MANIFEST.in
README.md
requirements.txt
setup.cfg
setup.py
mcheck/__init__.py
mcheck/algorithm.py
mcheck/cli.py
mcheck/compute.py
mcheck/generate.py
mcheck/validate.py
mcheck.egg-info/PKG-INFO
mcheck.egg-info/SOURCES.txt
mcheck.egg-info/dependency_links.txt
mcheck.egg-info/entry_points.txt
mcheck.egg-info/requires.txt
mcheck.egg-info/top_level.txt