Metadata-Version: 1.1
Name: mcheck
Version: 0.0.2
Summary: A python package that can be installed with pip.
Home-page: https://github.com/coder-james/mcheck
Author: Yidong Ma
Author-email: 1120598207@qq.com
License: GPL
Platform: UNKNOWN
Classifier: Development Status :: 3 - Alpha
Classifier: Intended Audience :: Developers
Classifier: Programming Language :: Python :: 2.6
Classifier: Programming Language :: Python :: 2.7
Classifier: Programming Language :: Python :: 3
